djangocms_rawhtml/__init__.py
djangocms_rawhtml/cms_plugins.py
djangocms_rawhtml/models.py
djangocms_rawhtml/migrations/0001_rawhtmlplugindata.py
djangocms_rawhtml/migrations/0002_auto_20221216_1029.py
djangocms_rawhtml/migrations/0003_alter_rawhtmlplugindata_cmsplugin_ptr.py
djangocms_rawhtml/migrations/__init__.py
djangocms_rawhtml/templates/admin/djangocms_rawhtml/change_form.html
djangocms_rawhtml/templates/djangocms_rawhtml/plugins/raw.html
djangocms_rawhtml-1.3.0.dist-info/LICENSE
djangocms_rawhtml-1.3.0.dist-info/METADATA
djangocms_rawhtml-1.3.0.dist-info/WHEEL
djangocms_rawhtml-1.3.0.dist-info/top_level.txt
djangocms_rawhtml-1.3.0.dist-info/RECORD
