Metadata-Version: 2.1
Name: djangocms-rawhtml
Version: 1.3.0
Summary: Raw HTML Plugin for DjangoCMS with HTML code editor.
Home-page: https://github.com/ketaro/djangocms-rawhtml
Author: Nick Avgerinos
Author-email: nicka@axcella.com
License: BSD License
Platform: UNKNOWN
Classifier: Development Status :: 5 - Production/Stable
Classifier: Environment :: Web Environment
Classifier: Framework :: Django
Classifier: Framework :: Django :: 3.0
Classifier: Framework :: Django :: 3.1
Classifier: Framework :: Django :: 3.2
Classifier: Framework :: Django :: 4.0
Classifier: Framework :: Django :: 4.1
Classifier: Framework :: Django :: 4.2
Classifier: Framework :: Django CMS
Classifier: Framework :: Django CMS :: 3.8
Classifier: Framework :: Django CMS :: 3.9
Classifier: Framework :: Django CMS :: 3.10
Classifier: Framework :: Django CMS :: 3.11
Classifier: Intended Audience :: Developers
Classifier: License :: OSI Approved :: BSD License
Classifier: Operating System :: OS Independent
Classifier: Programming Language :: Python
Classifier: Programming Language :: Python :: 3.6
Classifier: Programming Language :: Python :: 3.7
Classifier: Programming Language :: Python :: 3.8
Classifier: Programming Language :: Python :: 3.9
Classifier: Topic :: Internet :: WWW/HTTP
Classifier: Topic :: Internet :: WWW/HTTP :: Dynamic Content
